osas/__init__.py
osas/api.py
osas/cli.py
osas/webserver.py
osas/core/__init__.py
osas/core/anomaly.py
osas/core/interfaces.py
osas/core/label_generators.py
osas/core/utils.py
osas/data/__init__.py
osas/data/datasources.py
osas/io_utils/__init__.py
osas/io_utils/config.py
osas/io_utils/formatter.py
osas/main/__init__.py
osas/main/apply_rules.py
osas/main/autoconfig.py
osas/main/run_pipeline.py
osas/main/train_pipeline.py
osas/models/__init__.py
osas/models/pipeline.py
osas/pipeline/__init__.py
osas/pipeline/detect_anomalies.py
osas/pipeline/fetch_data.py
osas/pipeline/groom_data.py
osas/pipeline/pipeline.py
osas-0.9.3.dist-info/LICENSE
osas-0.9.3.dist-info/METADATA
osas-0.9.3.dist-info/WHEEL
osas-0.9.3.dist-info/entry_points.txt
osas-0.9.3.dist-info/top_level.txt
osas-0.9.3.dist-info/RECORD
