Metadata-Version: 2.1
Name: osas
Version: 0.9.3
Summary: One Stop Anomaly Shop
Home-page: https://github.com/adobe/OSAS/
Author: Multiple Authors
Author-email: boros@adobe.com
Project-URL: Source Code, https://github.com/adobe/OSAS/
Project-URL: Bug Tracker, https://github.com/adobe/OSAS/issues
Project-URL: Documentation, https://github.com/adobe/OSAS/docs/
Classifier: Programming Language :: Python :: 3.0
Classifier: License :: OSI Approved :: Apache Software License
Classifier: Operating System :: OS Independent
Requires-Python: >=3.10
License-File: LICENSE
Requires-Dist: click==8.1.8
Requires-Dist: elasticsearch==9.0.1
Requires-Dist: Flask==3.1.0
Requires-Dist: ipdb==0.13.13
Requires-Dist: numpy==2.2.5
Requires-Dist: obfuscation_detection==0.7.2
Requires-Dist: pandas==2.2.3
Requires-Dist: python-decouple==3.8
Requires-Dist: PyYAML==6.0.2
Requires-Dist: scikit_learn==1.6.1
Requires-Dist: setuptools==65.5.1
Requires-Dist: tqdm==4.67.1
